next_gen_ui_testing/__init__.py
next_gen_ui_testing/agent_testing.py
next_gen_ui_testing/data_after_transformation.py
next_gen_ui_testing/data_set_movies.py
next_gen_ui_testing/model.py
next_gen_ui_testing-0.3.0.dist-info/METADATA
next_gen_ui_testing-0.3.0.dist-info/WHEEL
next_gen_ui_testing-0.3.0.dist-info/namespace_packages.txt
next_gen_ui_testing-0.3.0.dist-info/top_level.txt
next_gen_ui_testing-0.3.0.dist-info/RECORD
